{
  "match_isbn": null,
  "dont": "0967865204",
  "is_community": false,
  "missing": "found no matches",
  "was_valid": "2013-12-11T03:49:55Z",
  "title": "Cottonwood Public Library",
  "problems": "Missing item found!\n",
  "problem_count": 53,
  "tested": "2015-06-26T07:13:07Z",
  "has_problems": true,
  "have": "0394839129",
  "name": "us.az.cottonwood_public_library",
  "country": "US",
  "state": "AZ",
  "linktemplate": "http://catalog.yln.info/uhtbin/cgisirsi/x/0/0/5?searchdata1={rft:isbn}&srchfield1=GENERAL^SUBJECT^GENERAL^^ISBN&library=CTW_SG"
}