{
  "dont": "0967865204",
  "missing": "No matches found",
  "was_valid": "2012-08-27T18:06:32Z",
  "title": "San Diego - Rancho Santa Fe Branch",
  "problems": "Existing item not found!\n",
  "problem_count": 98,
  "tested": "2015-07-03T10:02:06Z",
  "has_problems": true,
  "have": "0439139570",
  "name": "us.ca.sandiego.rancho_santa_fe_branch",
  "country": "US",
  "state": "CA",
  "linktemplate": "http://dbpcosdcsgt.co.san-diego.ca.us/search~S1/?searchtype=i&searcharg={rft:isbn}&searchscope=31"
}
