{
  "dont": "0967865204",
  "missing": "found no matches",
  "was_valid": "2012-07-24T23:35:56Z",
  "title": "Hamilton - ALL",
  "problems": "Missing item found!\n",
  "problem_count": 101,
  "tested": "2015-07-01T11:32:01Z",
  "has_problems": true,
  "have": "0439136350",
  "name": "us.oh.hamilton_county_all",
  "country": "US",
  "state": "OH",
  "linktemplate": "http://catalog.cincinnatilibrary.org/uhtbin/cgisirsi/x/0/0/5?searchdata1={rft:isbn}&srchfield1=GENERAL^SUBJECT^GENERAL^^ISBN&library=ALL"
}
