{
  "dont": "0967865204",
  "missing": "found no matches",
  "was_valid": "2011-11-03T13:27:25Z",
  "title": "LS - Muscatine Community College",
  "problems": "Deadline exceeded while waiting for HTTP response from URL: http://216.125.140.44/uhtbin/cgisirsi/x/0/0/123?searchdata1=067121781X&srchfield1=GENERAL^SUBJECT^GENERAL^^ISBN&library=MCCG-8&sort_by=ANY%27",
  "tested": "2015-06-26T11:28:23Z",
  "have": "067121781X",
  "name": "us.pals.muscatine_community_college",
  "country": "US",
  "state": "PA",
  "linktemplate": "http://216.125.140.44/uhtbin/cgisirsi/x/0/0/123?searchdata1={rft:isbn}&srchfield1=GENERAL^SUBJECT^GENERAL^^ISBN&library=MCCG-8&sort_by=ANY%27"
}
