{
  "dont": "0967865204",
  "missing": "found no matches",
  "was_valid": "2011-11-07T01:59:04Z",
  "title": "Greenwood Elementary School",
  "problems": "Deadline exceeded while waiting for HTTP response from URL: http://catalog.henrico.k12.va.us/uhtbin/cgisirsi/x/0/0/123?searchdata1=0590353403&srchfield1=GENERAL^SUBJECT^GENERAL^^ISBN&library=GREENWOOD",
  "tested": "2015-06-24T14:43:14Z",
  "have": "0590353403",
  "name": "us.va.greenwood_elementary_school",
  "country": "US",
  "state": "VA",
  "linktemplate": "http://catalog.henrico.k12.va.us/uhtbin/cgisirsi/x/0/0/123?searchdata1={rft:isbn}&srchfield1=GENERAL^SUBJECT^GENERAL^^ISBN&library=GREENWOOD"
}
