{
  "match_isbn": null,
  "dont": "0967865204",
  "is_community": false,
  "missing": "found no matches",
  "was_valid": "2014-08-11T12:08:30Z",
  "title": "Crook Co. SD1 - Moorcroft Elem School",
  "problems": "Existing item not found!\n",
  "problem_count": 30,
  "tested": "2015-06-25T12:58:12Z",
  "has_problems": true,
  "have": "0439139600",
  "name": "us.wy.crksd-moel",
  "country": "US",
  "state": "WY",
  "linktemplate": "http://wyld.state.wy.us/uhtbin/cgisirsi/x/0/0/57/5?user_id=crksd-moelweb&library=CRKSD-MOEL&searchdata1={rft:isbn}"
}